mushroom_rl/__init__.py
mushroom_rl/algorithms/__init__.py
mushroom_rl/algorithms/agent.py
mushroom_rl/algorithms/actor_critic/__init__.py
mushroom_rl/algorithms/actor_critic/classic_actor_critic/__init__.py
mushroom_rl/algorithms/actor_critic/classic_actor_critic/copdac_q.py
mushroom_rl/algorithms/actor_critic/classic_actor_critic/stochastic_ac.py
mushroom_rl/algorithms/actor_critic/deep_actor_critic/__init__.py
mushroom_rl/algorithms/actor_critic/deep_actor_critic/a2c.py
mushroom_rl/algorithms/actor_critic/deep_actor_critic/ddpg.py
mushroom_rl/algorithms/actor_critic/deep_actor_critic/deep_actor_critic.py
mushroom_rl/algorithms/actor_critic/deep_actor_critic/ppo.py
mushroom_rl/algorithms/actor_critic/deep_actor_critic/sac.py
mushroom_rl/algorithms/actor_critic/deep_actor_critic/td3.py
mushroom_rl/algorithms/actor_critic/deep_actor_critic/trpo.py
mushroom_rl/algorithms/policy_search/__init__.py
mushroom_rl/algorithms/policy_search/black_box_optimization/__init__.py
mushroom_rl/algorithms/policy_search/black_box_optimization/black_box_optimization.py
mushroom_rl/algorithms/policy_search/black_box_optimization/pgpe.py
mushroom_rl/algorithms/policy_search/black_box_optimization/reps.py
mushroom_rl/algorithms/policy_search/black_box_optimization/rwr.py
mushroom_rl/algorithms/policy_search/policy_gradient/__init__.py
mushroom_rl/algorithms/policy_search/policy_gradient/enac.py
mushroom_rl/algorithms/policy_search/policy_gradient/gpomdp.py
mushroom_rl/algorithms/policy_search/policy_gradient/policy_gradient.py
mushroom_rl/algorithms/policy_search/policy_gradient/reinforce.py
mushroom_rl/algorithms/value/__init__.py
mushroom_rl/algorithms/value/batch_td/__init__.py
mushroom_rl/algorithms/value/batch_td/batch_td.py
mushroom_rl/algorithms/value/batch_td/fqi.py
mushroom_rl/algorithms/value/batch_td/lspi.py
mushroom_rl/algorithms/value/dqn/__init__.py
mushroom_rl/algorithms/value/dqn/categorical_dqn.py
mushroom_rl/algorithms/value/dqn/dqn.py
mushroom_rl-1.4.0.dist-info/DESCRIPTION.rst
mushroom_rl-1.4.0.dist-info/METADATA
mushroom_rl-1.4.0.dist-info/RECORD
mushroom_rl-1.4.0.dist-info/WHEEL
mushroom_rl-1.4.0.dist-info/metadata.json
mushroom_rl-1.4.0.dist-info/top_level.txt
