Metadata-Version: 2.0
Name: mushroom-rl
Version: 1.4.0
Summary: A Python toolkit for Reinforcement Learning experiments.
Home-page: https://github.com/MushroomRL/mushroom-rl
Author: Carlo D'Eramo
Author-email: carlo.deramo@gmail.com
License: MIT
Platform: UNKNOWN
Classifier: Programming Language :: Python :: 3
Classifier: License :: OSI Approved :: MIT License
Classifier: Operating System :: OS Independent
Provides-Extra: gym
Provides-Extra: atari
Provides-Extra: box2d
Provides-Extra: bullet
Provides-Extra: mujoco
Provides-Extra: plots
Provides-Extra: all
Requires-Dist: numpy
Requires-Dist: scipy
Requires-Dist: scikit-learn
Requires-Dist: matplotlib
Requires-Dist: joblib
Requires-Dist: tqdm
Requires-Dist: pygame
Requires-Dist: opencv-python
Requires-Dist: torch
Requires-Dist: pytest
Provides-Extra: all
Requires-Dist: gym; extra == 'all'
Requires-Dist: atari-py (~=0.2.0); extra == 'all'
Requires-Dist: Pillow; extra == 'all'
Requires-Dist: opencv-python; extra == 'all'
Requires-Dist: box2d-py (~=2.3.5); extra == 'all'
Requires-Dist: pybullet; extra == 'all'
Provides-Extra: atari
Requires-Dist: atari-py (~=0.2.0); extra == 'atari'
Requires-Dist: Pillow; extra == 'atari'
Requires-Dist: opencv-python; extra == 'atari'
Provides-Extra: box2d
Requires-Dist: box2d-py (~=2.3.5); extra == 'box2d'
Provides-Extra: bullet
Requires-Dist: pybullet; extra == 'bullet'
Provides-Extra: gym
Requires-Dist: gym; extra == 'gym'
Provides-Extra: mujoco
Requires-Dist: mujoco-py; extra == 'mujoco'
Provides-Extra: plots
Requires-Dist: pyqtgraph; extra == 'plots'
